tarun/__init__.py
tarun/run.py
tarun-0.1.2.dist-info/METADATA
tarun-0.1.2.dist-info/WHEEL
tarun-0.1.2.dist-info/entry_points.txt
tarun-0.1.2.dist-info/top_level.txt
tarun-0.1.2.dist-info/RECORD
