Metadata-Version: 2.1
Name: tarun
Version: 0.1.2
Summary: Extract many style file
Home-page: https://github.com/wangyu190810/tarun
Author: 22too
Author-email: info@22too.com
License: MIT
Platform: UNKNOWN
Classifier: Programming Language :: Python :: 3
Classifier: License :: OSI Approved :: MIT License
Classifier: Operating System :: OS Independent
